pyarchery/__init__.py
pyarchery/config.py
pyarchery/dependencies
pyarchery/dependencies.sha256
pyarchery/download.py
pyarchery/jvm.py
pyarchery/py.typed
pyarchery/version.py
pyarchery/wrappers.py
pyarchery/archery/__init__.py
pyarchery/archery/classes.py
pyarchery/archery/defines.py
pyarchery/archery/java_types.py
pyarchery.libs/xelem-3.1.jar
pyjarchery-0.1.16.dist-info/METADATA
pyjarchery-0.1.16.dist-info/WHEEL
pyjarchery-0.1.16.dist-info/licenses/LICENSE
pyjarchery-0.1.16.dist-info/RECORD
