Metadata-Version: 2.4
Name: pyjarchery
Version: 0.1.16
Summary: Python binding to Java Archery Framework
Author-email: Romuald Rousseau <romuald.rousseau@servier.com>
License-File: LICENSE
Requires-Python: ~=3.11.0
Requires-Dist: jpype1>=1.6.0
Requires-Dist: pyarrow>=22.0.0
Requires-Dist: requests>=2.32.5
Requires-Dist: tqdm>=4.67.1
